AutoChromedriver2/__init__.py
AutoChromedriver2/chromedriver_check.py
AutoChromedriver2-0.1.dist-info/LICENSE
AutoChromedriver2-0.1.dist-info/METADATA
AutoChromedriver2-0.1.dist-info/WHEEL
AutoChromedriver2-0.1.dist-info/top_level.txt
AutoChromedriver2-0.1.dist-info/RECORD
